Metadata-Version: 1.0
Name: dist-prob-dst
Version: 1.2
Summary: Gaussian and Binomial distributions
Home-page: UNKNOWN
Author: Megha Raveendran
Author-email: UNKNOWN
License: UNKNOWN
Platform: UNKNOWN
